eth_rpc/__init__.py
eth_rpc/_request.py
eth_rpc/_response.py
eth_rpc/_transport.py
eth_rpc/account.py
eth_rpc/block.py
eth_rpc/block_explorer.py
eth_rpc/codegen.py
eth_rpc/constants.py
eth_rpc/delegation.py
eth_rpc/event.py
eth_rpc/exceptions.py
eth_rpc/log.py
eth_rpc/main_cli.py
eth_rpc/py.typed
eth_rpc/transaction.py
eth_rpc/wallet.py
eth_rpc/contract/__init__.py
eth_rpc/contract/base.py
eth_rpc/contract/contract.py
eth_rpc/contract/eth_response.py
eth_rpc/contract/func_signature.py
eth_rpc/contract/function.py
eth_rpc/contract/interface.py
eth_rpc/ens/__init__.py
eth_rpc/ens/lookup.py
eth_rpc/models/__init__.py
eth_rpc/models/access_list.py
eth_rpc/models/account.py
eth_rpc/models/block.py
eth_rpc/models/fee_history.py
eth_rpc/models/log.py
eth_rpc/models/transaction.py
eth_rpc/models/transaction_receipt.py
eth_rpc/networks/__init__.py
eth_rpc/networks/arbitrum.py
eth_rpc/networks/avalanche.py
eth_rpc/networks/base.py
eth_rpc/networks/ethereum.py
eth_rpc/networks/linea.py
eth_rpc/networks/sapphire.py
eth_rpc/rpc/__init__.py
eth_rpc/rpc/base.py
eth_rpc/rpc/core.py
eth_rpc/rpc/method/__init__.py
eth_rpc/rpc/method/base.py
eth_rpc/subscriber/__init__.py
eth_rpc/subscriber/combinator.py
eth_rpc/subscriber/event_subscriber.py
eth_rpc/types/__init__.py
eth_rpc/types/basic.py
eth_rpc/types/error.py
eth_rpc/types/event.py
eth_rpc/types/network.py
eth_rpc/types/primitives.py
eth_rpc/types/response.py
eth_rpc/types/struct.py
eth_rpc/types/transaction.py
eth_rpc/types/typed_data.py
eth_rpc/types/args/__init__.py
eth_rpc/types/args/account.py
eth_rpc/types/args/alchemy.py
eth_rpc/types/args/block.py
eth_rpc/types/args/eth_call.py
eth_rpc/types/args/fee_history.py
eth_rpc/types/args/logs.py
eth_rpc/types/args/oasis.py
eth_rpc/types/args/storage.py
eth_rpc/types/args/tracer.py
eth_rpc/types/args/transaction.py
eth_rpc/utils/__init__.py
eth_rpc/utils/address.py
eth_rpc/utils/bloom.py
eth_rpc/utils/client.py
eth_rpc/utils/datetime.py
eth_rpc/utils/dual_async.py
eth_rpc_py-0.1.34.dist-info/METADATA
eth_rpc_py-0.1.34.dist-info/WHEEL
eth_rpc_py-0.1.34.dist-info/entry_points.txt
eth_rpc_py-0.1.34.dist-info/top_level.txt
eth_rpc_py-0.1.34.dist-info/RECORD
